igeGameAnalytics.cp37-win32.pyd
igeGameAnalytics-0.0.3.dist-info/LICENSE
igeGameAnalytics-0.0.3.dist-info/METADATA
igeGameAnalytics-0.0.3.dist-info/WHEEL
igeGameAnalytics-0.0.3.dist-info/top_level.txt
igeGameAnalytics-0.0.3.dist-info/RECORD
